streamlit_vertical_slider/__init__.py
streamlit_vertical_slider/frontend/build/asset-manifest.json
streamlit_vertical_slider/frontend/build/bootstrap.min.css
streamlit_vertical_slider/frontend/build/index.html
streamlit_vertical_slider/frontend/build/precache-manifest.acd16c8635e1d879ef64661a2b248e7b.js
streamlit_vertical_slider/frontend/build/service-worker.js
streamlit_vertical_slider/frontend/build/static/js/2.0b0a3dec.chunk.js
streamlit_vertical_slider/frontend/build/static/js/2.0b0a3dec.chunk.js.LICENSE.txt
streamlit_vertical_slider/frontend/build/static/js/2.0b0a3dec.chunk.js.map
streamlit_vertical_slider/frontend/build/static/js/main.39569fff.js
streamlit_vertical_slider/frontend/build/static/js/main.39569fff.js.LICENSE.txt
streamlit_vertical_slider/frontend/build/static/js/main.39569fff.js.map
streamlit_vertical_slider/frontend/build/static/js/main.749ca5aa.js
streamlit_vertical_slider/frontend/build/static/js/main.749ca5aa.js.LICENSE.txt
streamlit_vertical_slider/frontend/build/static/js/main.749ca5aa.js.map
streamlit_vertical_slider/frontend/build/static/js/main.9f60d05d.chunk.js
streamlit_vertical_slider/frontend/build/static/js/main.9f60d05d.chunk.js.map
streamlit_vertical_slider/frontend/build/static/js/runtime-main.6ec50d9a.js
streamlit_vertical_slider/frontend/build/static/js/runtime-main.6ec50d9a.js.map
streamlit_vertical_slider-2.5.5.dist-info/LICENSE
streamlit_vertical_slider-2.5.5.dist-info/METADATA
streamlit_vertical_slider-2.5.5.dist-info/WHEEL
streamlit_vertical_slider-2.5.5.dist-info/top_level.txt
streamlit_vertical_slider-2.5.5.dist-info/RECORD
