Metadata-Version: 2.1
Name: streamlit_vertical_slider
Version: 2.5.5
Summary: Creates a customizable vertical slider
Home-page: https://github.com/sqlinsights/streamlit-vertical-slider
Author: Carlos D. Serrano
Author-email: sqlinsights@gmail.com
Requires-Python: >=3.8
License-File: LICENSE
